markymark/__init__.py
markymark/extensions/__init__.py
markymark/extensions/anylink.py
markymark/extensions/autolink.py
markymark/extensions/base.py
markymark/extensions/clean.py
markymark/extensions/filer.py
markymark/fields.py
markymark/renderer.py
markymark/static/markymark/css/markdown-editor.css
markymark/static/markymark/extensions/anylink.js
markymark/static/markymark/extensions/clean.js
markymark/static/markymark/extensions/filer.css
markymark/static/markymark/extensions/filer.js
markymark/static/markymark/fontawesome/LICENSE.txt
markymark/static/markymark/fontawesome/fa-brands-400.woff
markymark/static/markymark/fontawesome/fa-regular-400.woff
markymark/static/markymark/fontawesome/fa-solid-900.woff
markymark/static/markymark/fontawesome/fontawesome.min.css
markymark/static/markymark/js/markdown-editor.js
markymark/templates/markymark/anylink.html
markymark/templates/markymark/autolink.html
markymark/templates/markymark/filer.html
markymark/templatetags/__init__.py
markymark/templatetags/markymark.py
markymark/widgets.py
django_markymark-4.0.2.dist-info/METADATA
django_markymark-4.0.2.dist-info/WHEEL
django_markymark-4.0.2.dist-info/licenses/LICENSE.rst
django_markymark-4.0.2.dist-info/RECORD
