Metadata-Version: 2.4
Name: django-markymark
Version: 4.0.2
Summary: django-markymark provides helpers and tools to integrate markdown.
License: MIT
License-File: LICENSE.rst
Author: Stephan Jaekel
Author-email: steph@rdev.info
Requires-Python: >=3.10,<4
Classifier: Development Status :: 5 - Production/Stable
Classifier: Environment :: Web Environment
Classifier: Framework :: Django
Classifier: Intended Audience :: Developers
Classifier: License :: OSI Approved :: MIT License
Classifier: Operating System :: Unix
Classifier: Programming Language :: Python
Classifier: Programming Language :: Python :: 3
Classifier: Programming Language :: Python :: 3.10
Classifier: Programming Language :: Python :: 3.11
Classifier: Programming Language :: Python :: 3.12
Classifier: Programming Language :: Python :: 3.13
Classifier: Programming Language :: Python :: 3.14
Provides-Extra: docs
Requires-Dist: Django (>=4.2,<6)
Requires-Dist: Markdown (>=3.4)
Requires-Dist: Sphinx (>=5.1) ; extra == "docs"
Requires-Dist: django-anylink (>=2.0.1) ; extra == "docs"
Requires-Dist: django-filer (>=2.2.3) ; extra == "docs"
Project-URL: Homepage, https://github.com/stephrdev/django-markymark
Project-URL: Repository, https://github.com/stephrdev/django-markymark
